switchbot_client/__init__.py
switchbot_client/api.py
switchbot_client/client.py
switchbot_client/constants.py
switchbot_client/devices/__init__.py
switchbot_client/devices/base.py
switchbot_client/devices/factory.py
switchbot_client/devices/physical.py
switchbot_client/devices/remote.py
switchbot_client/devices/status.py
switchbot_client/enums.py
switchbot_client/scenes/__init__.py
switchbot_client/scenes/base.py
switchbot_client/types.py
switchbot_client/webhooks/__init__.py
switchbot_client/webhooks/base.py
switchbot_client-0.4.1.dist-info/WHEEL
switchbot_client-0.4.1.dist-info/METADATA
switchbot_client-0.4.1.dist-info/RECORD
