Metadata-Version: 2.1
Name: switchbot-client
Version: 0.4.1
Summary: A Python client library for SwitchBot API.
Home-page: https://github.com/kzosabe/switchbot-client
License: Apache-2.0 or MIT
Author: Kazuhito Osabe
Author-email: kzosabe@wip.place
Requires-Python: >=3.7,<4.0
Classifier: Development Status :: 4 - Beta
Classifier: Intended Audience :: Developers
Classifier: Intended Audience :: End Users/Desktop
Classifier: License :: OSI Approved :: Apache Software License
Classifier: License :: OSI Approved :: MIT License
Classifier: License :: Other/Proprietary License
Classifier: Operating System :: OS Independent
Classifier: Programming Language :: Python :: 3
Classifier: Programming Language :: Python :: 3.7
Classifier: Programming Language :: Python :: 3.8
Classifier: Programming Language :: Python :: 3.9
Classifier: Programming Language :: Python :: 3.10
Classifier: Topic :: Software Development :: Libraries :: Python Modules
Requires-Dist: PyYAML (>=5.4.1,<7.0.0)
Requires-Dist: requests (>=2.0,<3.0)
Requires-Dist: typing-extensions (>=3.10,<5.0)
Project-URL: Repository, https://github.com/kzosabe/switchbot-client
